dlxsudoku/__init__.py
dlxsudoku/dancing_links.py
dlxsudoku/exceptions.py
dlxsudoku/sudoku.py
dlxsudoku/utils.py
dlxsudoku-0.10.3.dist-info/DESCRIPTION.rst
dlxsudoku-0.10.3.dist-info/METADATA
dlxsudoku-0.10.3.dist-info/RECORD
dlxsudoku-0.10.3.dist-info/WHEEL
dlxsudoku-0.10.3.dist-info/entry_points.txt
dlxsudoku-0.10.3.dist-info/metadata.json
dlxsudoku-0.10.3.dist-info/top_level.txt
