Metadata-Version: 2.0
Name: dlxsudoku
Version: 0.10.3
Summary: Sudoku Solver in pure Python with no dependencies
Home-page: https://github.com/hbldh/dlxsudoku
Author: Henrik Blidh
Author-email: henrik.blidh@nedomkull.com
License: GNU GPLv2
Keywords: sudoku,sudoku solver,dancing links
Platform: UNKNOWN
Classifier: Development Status :: 4 - Beta
Classifier: Operating System :: OS Independent
Classifier: License :: OSI Approved :: GNU General Public License v2 (GPLv2)
Classifier: Programming Language :: Python :: 2
Classifier: Programming Language :: Python :: 2.7
Classifier: Programming Language :: Python :: 3
Classifier: Programming Language :: Python :: 3.3
Classifier: Programming Language :: Python :: 3.4
Classifier: Programming Language :: Python :: 3.5
Classifier: Intended Audience :: Developers
